ida_parse_trace_line_helper/__init__.py
ida_parse_trace_line_helper/operand.py
ida_parse_trace_line_helper/trace_line_info.py
ida_parse_trace_line_helper/trace_line_parser.py
tests/__init__.py
ida_parse_trace_line_helper-0.0.8.dist-info/METADATA
ida_parse_trace_line_helper-0.0.8.dist-info/WHEEL
ida_parse_trace_line_helper-0.0.8.dist-info/top_level.txt
ida_parse_trace_line_helper-0.0.8.dist-info/RECORD
