Metadata-Version: 2.1
Name: ida-parse-trace-line-helper
Version: 0.0.8
Summary: parse trace file
Home-page: https://github.com/BeyondMark/ida-parse-trace-file-helper.git
Author: beyond_mark
Author-email: luck.yangbo@gmail.com
License: UNKNOWN
Platform: UNKNOWN
Classifier: Programming Language :: Python :: 3
Classifier: License :: OSI Approved :: MIT License
Classifier: Operating System :: OS Independent
Requires-Python: >=3.7
